autocorrect_kh/__init__.py
autocorrect_kh/autocorrect.py
autocorrect_kh/data/district.txt
autocorrect_kh/data/province.txt
autocorrect_kh/data/khum/banteymeanchey.txt
autocorrect_kh/data/khum/battambang.txt
autocorrect_kh/data/khum/kampongcham.txt
autocorrect_kh/data/khum/kampongchnang.txt
autocorrect_kh/data/khum/kampongspeu.txt
autocorrect_kh/data/khum/kampongthom.txt
autocorrect_kh/data/khum/kampot.txt
autocorrect_kh/data/khum/kandal.txt
autocorrect_kh/data/khum/kep.txt
autocorrect_kh/data/khum/kohkong.txt
autocorrect_kh/data/khum/kratie.txt
autocorrect_kh/data/khum/mundulkiri.txt
autocorrect_kh/data/khum/ordomeanchey.txt
autocorrect_kh/data/khum/pailin.txt
autocorrect_kh/data/khum/phnompenh.txt
autocorrect_kh/data/khum/preahsihanouk.txt
autocorrect_kh/data/khum/preahvihear.txt
autocorrect_kh/data/khum/preyveng.txt
autocorrect_kh/data/khum/pursat.txt
autocorrect_kh/data/khum/ratanakiri.txt
autocorrect_kh/data/khum/siemreap.txt
autocorrect_kh/data/khum/stungtraeng.txt
autocorrect_kh/data/khum/svayrieng.txt
autocorrect_kh/data/khum/takeo.txt
autocorrect_kh/data/khum/tbongkhmum.txt
autocorrect_kh/data/phum/banteymeanchey.txt
autocorrect_kh/data/phum/battambang.txt
autocorrect_kh/data/phum/kampongcham.txt
autocorrect_kh/data/phum/kampongchnang.txt
autocorrect_kh/data/phum/kampongspeu.txt
autocorrect_kh/data/phum/kampongthom.txt
autocorrect_kh/data/phum/kampot.txt
autocorrect_kh/data/phum/kandal.txt
autocorrect_kh/data/phum/kep.txt
autocorrect_kh/data/phum/kohkong.txt
autocorrect_kh/data/phum/kratie.txt
autocorrect_kh/data/phum/mundulkiri.txt
autocorrect_kh/data/phum/ordomeanchey.txt
autocorrect_kh/data/phum/pailin.txt
autocorrect_kh/data/phum/phnompenh.txt
autocorrect_kh/data/phum/preahsihanouk.txt
autocorrect_kh/data/phum/preahvihear.txt
autocorrect_kh/data/phum/preyveng.txt
autocorrect_kh/data/phum/pursat.txt
autocorrect_kh/data/phum/ratanakiri.txt
autocorrect_kh/data/phum/siemreap.txt
autocorrect_kh/data/phum/stungtraeng.txt
autocorrect_kh/data/phum/svayrieng.txt
autocorrect_kh-0.3.1.dist-info/METADATA
autocorrect_kh-0.3.1.dist-info/WHEEL
autocorrect_kh-0.3.1.dist-info/top_level.txt
autocorrect_kh-0.3.1.dist-info/RECORD
