Metadata-Version: 2.1
Name: autocorrect-kh
Version: 0.3.1
Summary: An autocorrect Khmer Address and Specifically for Khmer National ID Card
Home-page: https://github.com/monykappa/autocorrect-kh.git
Author: Kim Ouddommony
Author-email: kimmony039@gmail.com
Requires-Dist: jellyfish
Requires-Dist: regex
